taxonomical_utils/__init__.py
taxonomical_utils/cli.py
taxonomical_utils/downloader.py
taxonomical_utils/exceptions.py
taxonomical_utils/foo.py
taxonomical_utils/merger.py
taxonomical_utils/nb.py
taxonomical_utils/processor.py
taxonomical_utils/resolver.py
taxonomical_utils/shared.py
taxonomical_utils/upper_taxa_lineage_appender.py
taxonomical_utils/wikidata_fetcher.py
taxonomical_utils-0.10.3.dist-info/LICENSE
taxonomical_utils-0.10.3.dist-info/METADATA
taxonomical_utils-0.10.3.dist-info/WHEEL
taxonomical_utils-0.10.3.dist-info/entry_points.txt
taxonomical_utils-0.10.3.dist-info/RECORD
