Metadata-Version: 2.1
Name: taxonomical_utils
Version: 0.10.3
Summary: A set of Python scripts to proceed to taxonomical resolution and retrieval of upper taxonomies.
Home-page: https://github.com/digital-botanical-gardens-initiative/taxonomical-utils
Author: Pierre-Marie Allard
Author-email: fpierre-marie.allard@unifr.ch
Requires-Python: >=3.10,<4.0
Classifier: Programming Language :: Python :: 3
Classifier: Programming Language :: Python :: 3.10
Classifier: Programming Language :: Python :: 3.11
Classifier: Programming Language :: Python :: 3.12
Requires-Dist: click (>=8.1.7,<9.0.0)
Requires-Dist: opentree (>=1.0.1,<2.0.0)
Requires-Dist: pandas (>=2.2.2,<3.0.0)
Requires-Dist: requests (>=2.32.2,<3.0.0)
Project-URL: Documentation, https://digital-botanical-gardens-initiative.github.io/taxonomical-utils/
Project-URL: Repository, https://github.com/digital-botanical-gardens-initiative/taxonomical-utils
